bullkpy/__init__.py
bullkpy/_jupyter.py
bullkpy/_settings.py
bullkpy/io.py
bullkpy/logging.py
bullkpy/_settings/__init__.py
bullkpy/_settings/verbosity.py
bullkpy/get/__init__.py
bullkpy/get/obs_df.py
bullkpy/get/rank_genes_groups_df.py
bullkpy/get/rank_genes_groups_df_all.py
bullkpy/get/vector.py
bullkpy/pl/__init__.py
bullkpy/pl/_colors.py
bullkpy/pl/_de_utils.py
bullkpy/pl/_style.py
bullkpy/pl/ari_resolution_heatmap.py
bullkpy/pl/association.py
bullkpy/pl/association_rankplots.py
bullkpy/pl/corr_heatmap.py
bullkpy/pl/corrplot_obs.py
bullkpy/pl/de.py
bullkpy/pl/dotplot.py
bullkpy/pl/gene_association.py
bullkpy/pl/gene_plot.py
bullkpy/pl/gsea_bubbleplot.py
bullkpy/pl/gsea_leading_edge.py
bullkpy/pl/heatmap_de.py
bullkpy/pl/oncoprint.py
bullkpy/pl/pca.py
bullkpy/pl/pca_loadings.py
bullkpy/pl/qc.py
bullkpy/pl/rank_genes_groups.py
bullkpy/pl/sample_distances.py
bullkpy/pl/umap.py
bullkpy/pl/violin.py
bullkpy/pl/volcano_categorical.py
bullkpy/plotting/_rcmod.py
bullkpy/pp/__init__.py
bullkpy/pp/batch.py
bullkpy/pp/filter.py
bullkpy/pp/hvg.py
bullkpy/pp/normalize.py
bullkpy/pp/qc.py
bullkpy/pp/sanitize.py
bullkpy/tl/__init__.py
bullkpy/tl/_nb_utils.py
bullkpy/tl/adjusted_rand_index.py
bullkpy/tl/association.py
bullkpy/tl/association_posthoc.py
bullkpy/tl/associations.py
bullkpy/tl/categorical_association.py
bullkpy/tl/cluster_metrics.py
bullkpy/tl/clustering.py
bullkpy/tl/correlations.py
bullkpy/tl/de.py
bullkpy/tl/de_glm.py
bullkpy/tl/gsea_MM.py
bullkpy/tl/gsea_prerank.py
bullkpy/tl/leiden_scan.py
bullkpy/tl/neighbors.py
bullkpy/tl/pca.py
bullkpy/tl/posthoc.py
bullkpy/tl/rank_genes_groups.py
bullkpy/tl/score_genes.py
bullkpy/tl/umap.py
bullkpy/tools/__init__.py
bullkpy-0.0.1.dist-info/licenses/LICENSE
bullkpy-0.0.1.dist-info/METADATA
bullkpy-0.0.1.dist-info/WHEEL
bullkpy-0.0.1.dist-info/top_level.txt
bullkpy-0.0.1.dist-info/RECORD
