Metadata-Version: 2.4
Name: bullkpy
Version: 0.0.1
Summary: Scanpy-like pipeline for bulk RNA-seq in Python
Author: Marcos Malumbres
License: BSD 3-Clause License
Project-URL: Homepage, https://github.com/malumbres/BULLKpy
Project-URL: Repository, https://github.com/malumbres/BULLKpy
Project-URL: Issues, https://github.com/malumbres/BULLKpy/issues
Keywords: bulk-rnaseq,tcga,anndata,scanpy,bioinformatics
Classifier: Programming Language :: Python :: 3
Classifier: Programming Language :: Python :: 3 :: Only
Classifier: License :: OSI Approved :: MIT License
Classifier: Operating System :: OS Independent
Classifier: Intended Audience :: Science/Research
Classifier: Topic :: Scientific/Engineering :: Bio-Informatics
Requires-Python: >=3.9
License-File: LICENSE
Requires-Dist: numpy
Requires-Dist: pandas
Requires-Dist: scipy
Requires-Dist: matplotlib
Requires-Dist: anndata
Requires-Dist: seaborn
Requires-Dist: scikit-learn
Requires-Dist: statsmodels
Requires-Dist: gseapy
Provides-Extra: dev
Requires-Dist: pytest; extra == "dev"
Requires-Dist: ruff; extra == "dev"
Requires-Dist: black; extra == "dev"
Requires-Dist: build; extra == "dev"
Requires-Dist: twine; extra == "dev"
Provides-Extra: docs
Requires-Dist: sphinx<8,>=7; extra == "docs"
Requires-Dist: pydata-sphinx-theme>=0.15; extra == "docs"
Requires-Dist: myst-parser<4,>=2; extra == "docs"
Requires-Dist: myst-nb<1.3,>=1.1; extra == "docs"
Requires-Dist: sphinx-autodoc-typehints; extra == "docs"
Requires-Dist: sphinx-copybutton>=0.5; extra == "docs"
Requires-Dist: sphinx-design>=0.6; extra == "docs"
Dynamic: license-file
